django_admin_models_search/__init__.py
django_admin_models_search/tests.py
django_admin_models_search/urls.py
django_admin_models_search/views.py
django_admin_models_search/templates/admin/base_site.html
django_admin_models_search-1.0.1.post1.dist-info/licenses/LICENCE
django_admin_models_search-1.0.1.post1.dist-info/METADATA
django_admin_models_search-1.0.1.post1.dist-info/WHEEL
django_admin_models_search-1.0.1.post1.dist-info/top_level.txt
django_admin_models_search-1.0.1.post1.dist-info/RECORD
